Metadata-Version: 1.1
Name: gpiochip2
Version: 0.9.3
Summary: Pythonic API for Linux's gpiochip chardev ABI v2.
Home-page: http://github.com/vpelletier/python-gpiochip2
Author: Vincent Pelletier
Author-email: plr.vincent@gmail.com
License: GPLv3+
Keywords: linux gpiochip chardev
Platform: linux
Classifier: Intended Audience :: Developers
Classifier: License :: OSI Approved :: GNU General Public License v3 or later (GPLv3+)
Classifier: Operating System :: POSIX :: Linux
Classifier: Programming Language :: Python :: 3
Classifier: Programming Language :: Python :: Implementation :: CPython
Classifier: Programming Language :: Python :: Implementation :: PyPy
Classifier: Topic :: Software Development :: Libraries
Classifier: Topic :: System :: Hardware :: Hardware Drivers
